sensorpi/__init__.py
sensorpi/__main__.py
sensorpi/flycheck___init__.py
sensorpi/flycheck___main__.py
sensorpi/sensors/#a8d29699ccf3fe203a664963bb1eafe99ff91cc3#
sensorpi/sensors/__init__.py
sensorpi/sensors/bme280.py
sensorpi/sensors/bmp280.py
sensorpi/sensors/camera.py
sensorpi/sensors/dht11.py
sensorpi/sensors/ds18b20.py
sensorpi/sensors/handler.py
sensorpi/sensors/tsl2591.py
sensorpi-0.1.6.dist-info/entry_points.txt
sensorpi-0.1.6.dist-info/LICENSE
sensorpi-0.1.6.dist-info/WHEEL
sensorpi-0.1.6.dist-info/METADATA
sensorpi-0.1.6.dist-info/RECORD
