Metadata-Version: 2.1
Name: sensorpi
Version: 0.1.6
Summary: A Raspberry Pi tool to send multiple sensor data to an influxdb Database
Home-page: https://github.com/weidtn/sensorpi/
License: MPL-2.0
Author: Nikolai Weidt
Author-email: weidtn@gmail.com
Maintainer: Nikolai Weidt
Maintainer-email: weidtn@gmail.com
Requires-Python: >=3.9,<4.0
Classifier: License :: OSI Approved
Classifier: Programming Language :: Python :: 3
Classifier: Programming Language :: Python :: 3.10
Classifier: Programming Language :: Python :: 3.9
Requires-Dist: adafruit-circuitpython-bme280 (>=2.6,<3.0)
Requires-Dist: adafruit-circuitpython-bmp280 (>=3.2,<4.0)
Requires-Dist: adafruit-circuitpython-dht (>=3.7.1,<4.0.0)
Requires-Dist: adafruit-circuitpython-tsl2591 (>=1.3.2,<2.0.0)
Requires-Dist: edn_format (>=0.7,<0.8)
Requires-Dist: influxdb-client[ciso] (>=1.25,<2.0)
Requires-Dist: numpy (>=1.22,<2.0)
Requires-Dist: opencv-python-headless (==4.5.5.62)
Requires-Dist: pandas (>=1.4,<2.0)
Requires-Dist: picamera (==1.13)
Requires-Dist: sysv-ipc (>=1.1,<2.0)
Project-URL: Repository, https://github.com/weidtn/sensorpi/
Project-URL: issues, https://github.com/weidtn/sensorpi/issues
